{
  "api_name": "上海黄金基础信息",
  "api_code": "sge_basic",
  "description": "获取上海黄金交易所现货合约基础信息",
  "__describe__": {
    "url": "https://tushare.pro/document/2?doc_id=284",
    "name": "上海黄金基础信息",
    "category": "现货数据___spot"
  },
  "request_params": [
    {
      "name": "ts_code",
      "type": "str",
      "description": "合约代码 （支持多个，逗号分隔，不输入为获取全部）",
      "required": false
    }
  ],
  "response_fields": [
    {
      "name": "ts_code",
      "type": "str",
      "description": "品种代码",
      "default_display": true
    },
    {
      "name": "ts_name",
      "type": "str",
      "description": "品种名称",
      "default_display": true
    },
    {
      "name": "trade_type",
      "type": "str",
      "description": "交易类型",
      "default_display": true
    },
    {
      "name": "t_unit",
      "type": "float",
      "description": "交易单位(克/手)",
      "default_display": true
    },
    {
      "name": "p_unit",
      "type": "float",
      "description": "报价单位",
      "default_display": true
    },
    {
      "name": "min_change",
      "type": "float",
      "description": "最小变动价位",
      "default_display": true
    },
    {
      "name": "price_limit",
      "type": "float",
      "description": "每日价格最大波动限制",
      "default_display": true
    },
    {
      "name": "min_vol",
      "type": "int",
      "description": "最小单笔报价量(手)",
      "default_display": true
    },
    {
      "name": "max_vol",
      "type": "int",
      "description": "最大单笔报价量(手)",
      "default_display": true
    },
    {
      "name": "trade_mode",
      "type": "str",
      "description": "交易期限",
      "default_display": true
    },
    {
      "name": "margin_rate",
      "type": "float",
      "description": "保证金比例",
      "default_display": true
    },
    {
      "name": "liq_rate",
      "type": "float",
      "description": "违约金比例(%)",
      "default_display": true
    },
    {
      "name": "trade_time",
      "type": "str",
      "description": "交易时间",
      "default_display": true
    },
    {
      "name": "list_date",
      "type": "str",
      "description": "上市日期",
      "default_display": true
    }
  ]
}