{
  "api_name": "港股日线行情",
  "api_code": "hk_daily",
  "description": "获取港股每日增量和历史行情，每日18点左右更新当日数据",
  "__describe__": {
    "url": "https://tushare.pro/document/2?doc_id=192",
    "name": "港股日线行情",
    "category": "港股数据___hk_stock"
  },
  "request_params": [
    {
      "name": "ts_code",
      "type": "str",
      "description": "股票代码",
      "required": false
    },
    {
      "name": "trade_date",
      "type": "str",
      "description": "交易日期",
      "required": false
    },
    {
      "name": "start_date",
      "type": "str",
      "description": "开始日期",
      "required": false
    },
    {
      "name": "end_date",
      "type": "str",
      "description": "结束日期",
      "required": false
    }
  ],
  "response_fields": [
    {
      "name": "ts_code",
      "type": "str",
      "description": "股票代码",
      "default_display": true
    },
    {
      "name": "trade_date",
      "type": "str",
      "description": "交易日期",
      "default_display": true
    },
    {
      "name": "open",
      "type": "float",
      "description": "开盘价",
      "default_display": true
    },
    {
      "name": "high",
      "type": "float",
      "description": "最高价",
      "default_display": true
    },
    {
      "name": "low",
      "type": "float",
      "description": "最低价",
      "default_display": true
    },
    {
      "name": "close",
      "type": "float",
      "description": "收盘价",
      "default_display": true
    },
    {
      "name": "pre_close",
      "type": "float",
      "description": "昨收价",
      "default_display": true
    },
    {
      "name": "change",
      "type": "float",
      "description": "涨跌额",
      "default_display": true
    },
    {
      "name": "pct_chg",
      "type": "float",
      "description": "涨跌幅(%)",
      "default_display": true
    },
    {
      "name": "vol",
      "type": "float",
      "description": "成交量(股)",
      "default_display": true
    },
    {
      "name": "amount",
      "type": "float",
      "description": "成交额(元)",
      "default_display": true
    }
  ]
}