{
  "api_name": "国债长期利率平均值",
  "api_code": "us_trltr",
  "description": "国债实际长期利率平均值",
  "__describe__": {
    "url": "https://tushare.pro/document/2?doc_id=223",
    "name": "国债长期利率平均值",
    "category": "美国利率___macro_us_rate"
  },
  "request_params": [
    {
      "name": "date",
      "type": "str",
      "description": "日期",
      "required": false
    },
    {
      "name": "start_date",
      "type": "str",
      "description": "开始日期",
      "required": false
    },
    {
      "name": "end_date",
      "type": "str",
      "description": "结束日期",
      "required": false
    },
    {
      "name": "fields",
      "type": "str",
      "description": "指定字段",
      "required": false
    }
  ],
  "response_fields": [
    {
      "name": "date",
      "type": "str",
      "description": "日期",
      "default_display": true
    },
    {
      "name": "ltr_avg",
      "type": "float",
      "description": "实际平均利率LT Real Average (10\u003e Yrs)",
      "default_display": true
    }
  ]
}